azure_recommendations_14/__init__.py
azure_recommendations_14/recommendation/__init__.py
azure_recommendations_14/recommendation/advisor_recommendations.py
azure_recommendations_14/recommendation/network_recommendations.py
azure_recommendations_14/recommendation/utils.py
azure_recommendations_14/recommendation/vm_recommendations.py
azure_recommendations_14-0.2.2.dist-info/LICENCE
azure_recommendations_14-0.2.2.dist-info/METADATA
azure_recommendations_14-0.2.2.dist-info/WHEEL
azure_recommendations_14-0.2.2.dist-info/top_level.txt
azure_recommendations_14-0.2.2.dist-info/RECORD
